<?xml version="1.0" encoding="UTF-8"?>
<avon total="7"><cover addtobag="1" category=""><limage url="assets/images/large/cover.jpg"/><mimage url="assets/images/medium/cover.jpg"/><simage url="assets/images/small/cover.jpg"/></cover><page addtobag="1" id="1" category=""><limage url="assets/images/large/002.jpg"/><mimage url="assets/images/medium/002.jpg"/><simage url="assets/images/small/002.jpg"/><product id="54866" name="სუნამოს წყალი Celebrate (სელებრეით) 50 мл" price="42.99" height="450" width="450" y="0" x="0"><subproduct id="73850" name="ტუალეტის წყალი Celebrate 75 мл" price="42.99" height="100" width="100" y="10" x="10"/></product><product id="42423" name="125 мл" price="34.99" height="450" width="450" y="0" x="429"><subproduct id="12997" name="ტუალეტის წყალი Black Suede Leather 75 мл" price="27.99" height="100" width="100" y="10" x="10"/><subproduct id="49342" name="ტუალეტის წყალი Black Suede Essential (ბლექ სუედე ესენშიალ) 75 мл" price="27.99" height="100" width="100" y="10" x="10"/><subproduct id="01851" name="სუნამოს წყალი Avon Cherish (ეივონ ჩერიშ) 50 мл" price="27.99" height="100" width="100" y="10" x="10"/><subproduct id="29957" name="სუნამოს წყალი Avon Cherish the Moment (ეივონ ჩერიშ ზი მომენთ) 50 мл" price="27.99" height="100" width="100" y="10" x="10"/><subproduct id="72469" name="ტუალეტის წყალი Black Suede Night (ბლექ სუიდ ნაით) 75 мл" price="27.99" height="100" width="100" y="10" x="10"/><subproduct id="35588" name="ტუალეტის წყალი Black Suede Touch (ბლექ სუიდ თაჩ) 75 мл" price="27.99" height="100" width="100" y="10" x="10"/><subproduct id="52660" name="ტუალეტის წყალი Black Suede Intense (ბლექ სუედე ინთენს) 75 мл" price="27.99" height="100" width="100" y="10" x="10"/></product></page><page addtobag="1" id="2" category=""><limage url="assets/images/large/004.jpg"/><mimage url="assets/images/medium/004.jpg"/><simage url="assets/images/small/004.jpg"/><product id="27424" name="" price="0" height="450" width="450" y="0" x="0"><subproduct id="09967" name="" price="0" height="100" width="100" y="10" x="10"/></product><product id="68974" name="" price="0" height="450" width="450" y="0" x="429"><subproduct id="59295" name="" price="0" height="100" width="100" y="10" x="10"/><subproduct id="60158" name="" price="0" height="100" width="100" y="10" x="10"/><subproduct id="71745" name="" price="0" height="100" width="100" y="10" x="10"/></product></page><page addtobag="1" id="3" category=""><limage url="assets/images/large/006.jpg"/><mimage url="assets/images/medium/006.jpg"/><simage url="assets/images/small/006.jpg"/><product id="91720" name="" price="0" height="450" width="450" y="0" x="429"><subproduct id="43834" name="" price="0" height="100" width="100" y="10" x="10"/><subproduct id="91707" name="" price="0" height="100" width="100" y="10" x="10"/><subproduct id="43846" name="" price="0" height="100" width="100" y="10" x="10"/><subproduct id="91713" name="" price="0" height="100" width="100" y="10" x="10"/><subproduct id="43883" name="" price="0" height="100" width="100" y="10" x="10"/></product></page><page addtobag="1" id="4" category=""><limage url="assets/images/large/008.jpg"/><mimage url="assets/images/medium/008.jpg"/><simage url="assets/images/small/008.jpg"/><product id="99736" name="" price="0" height="450" width="450" y="0" x="0"><subproduct id="98089" name="" price="0" height="100" width="100" y="10" x="10"/><subproduct id="99547" name="" price="0" height="100" width="100" y="10" x="10"/><subproduct id="98787" name="" price="0" height="100" width="100" y="10" x="10"/><subproduct id="98542" name="" price="0" height="100" width="100" y="10" x="10"/><subproduct id="98521" name="" price="0" height="100" width="100" y="10" x="10"/><subproduct id="98889" name="" price="0" height="100" width="100" y="10" x="10"/><subproduct id="99802" name="" price="0" height="100" width="100" y="10" x="10"/><subproduct id="99540" name="" price="0" height="100" width="100" y="10" x="10"/><subproduct id="99669" name="" price="0" height="100" width="100" y="10" x="10"/><subproduct id="99774" name="" price="0" height="100" width="100" y="10" x="10"/><subproduct id="99539" name="" price="0" height="100" width="100" y="10" x="10"/><subproduct id="98922" name="" price="0" height="100" width="100" y="10" x="10"/><subproduct id="44520" name="" price="0" height="100" width="100" y="10" x="10"/><subproduct id="98894" name="" price="0" height="100" width="100" y="10" x="10"/><subproduct id="99575" name="" price="0" height="100" width="100" y="10" x="10"/><subproduct id="99589" name="" price="0" height="100" width="100" y="10" x="10"/><subproduct id="98856" name="" price="0" height="100" width="100" y="10" x="10"/><subproduct id="99620" name="" price="0" height="100" width="100" y="10" x="10"/><subproduct id="99619" name="" price="0" height="100" width="100" y="10" x="10"/><subproduct id="98873" name="" price="0" height="100" width="100" y="10" x="10"/><subproduct id="98929" name="" price="0" height="100" width="100" y="10" x="10"/><subproduct id="99478" name="" price="0" height="100" width="100" y="10" x="10"/><subproduct id="99020" name="" price="0" height="100" width="100" y="10" x="10"/><subproduct id="99612" name="" price="0" height="100" width="100" y="10" x="10"/></product></page><page addtobag="1" id="5" category=""><limage url="assets/images/large/010.jpg"/><mimage url="assets/images/medium/010.jpg"/><simage url="assets/images/small/010.jpg"/><product id="70492" name="" price="0" height="450" width="450" y="0" x="429"><subproduct id="40319" name="" price="0" height="100" width="100" y="10" x="10"/><subproduct id="94598" name="" price="0" height="100" width="100" y="10" x="10"/><subproduct id="61189" name="" price="0" height="100" width="100" y="10" x="10"/><subproduct id="48371" name="" price="0" height="100" width="100" y="10" x="10"/><subproduct id="44697" name="" price="0" height="100" width="100" y="10" x="10"/><subproduct id="63669" name="" price="0" height="100" width="100" y="10" x="10"/><subproduct id="48372" name="" price="0" height="100" width="100" y="10" x="10"/><subproduct id="24669" name="" price="0" height="100" width="100" y="10" x="10"/><subproduct id="62713" name="" price="0" height="100" width="100" y="10" x="10"/><subproduct id="17508" name="" price="0" height="100" width="100" y="10" x="10"/><subproduct id="36738" name="" price="0" height="100" width="100" y="10" x="10"/><subproduct id="54056" name="" price="0" height="100" width="100" y="10" x="10"/><subproduct id="73085" name="" price="0" height="100" width="100" y="10" x="10"/><subproduct id="88546" name="" price="0" height="100" width="100" y="10" x="10"/><subproduct id="26194" name="" price="0" height="100" width="100" y="10" x="10"/><subproduct id="05924" name="" price="0" height="100" width="100" y="10" x="10"/><subproduct id="05780" name="" price="0" height="100" width="100" y="10" x="10"/><subproduct id="45530" name="" price="0" height="100" width="100" y="10" x="10"/><subproduct id="36420" name="" price="0" height="100" width="100" y="10" x="10"/><subproduct id="24900" name="" price="0" height="100" width="100" y="10" x="10"/><subproduct id="40510" name="" price="0" height="100" width="100" y="10" x="10"/><subproduct id="20902" name="" price="0" height="100" width="100" y="10" x="10"/><subproduct id="58556" name="" price="0" height="100" width="100" y="10" x="10"/><subproduct id="36419" name="0, мл" price="0.5" height="100" width="100" y="10" x="10"/><subproduct id="41492" name="" price="0" height="100" width="100" y="10" x="10"/><subproduct id="12410" name="" price="0" height="100" width="100" y="10" x="10"/><subproduct id="72384" name="" price="0" height="100" width="100" y="10" x="10"/><subproduct id="42944" name="" price="0" height="100" width="100" y="10" x="10"/><subproduct id="61708" name="" price="0" height="100" width="100" y="10" x="10"/><subproduct id="54055" name="" price="0" height="100" width="100" y="10" x="10"/><subproduct id="48597" name="" price="0" height="100" width="100" y="10" x="10"/><subproduct id="26996" name="" price="0" height="100" width="100" y="10" x="10"/><subproduct id="22247" name="" price="0" height="100" width="100" y="10" x="10"/><subproduct id="56868" name="" price="0" height="100" width="100" y="10" x="10"/><subproduct id="59953" name="" price="0" height="100" width="100" y="10" x="10"/><subproduct id="36552" name="" price="0" height="100" width="100" y="10" x="10"/><subproduct id="86214" name="" price="0" height="100" width="100" y="10" x="10"/><subproduct id="93976" name="" price="0" height="100" width="100" y="10" x="10"/><subproduct id="68979" name="" price="0" height="100" width="100" y="10" x="10"/><subproduct id="90680" name="" price="0" height="100" width="100" y="10" x="10"/><subproduct id="60624" name="" price="0" height="100" width="100" y="10" x="10"/><subproduct id="13075" name="" price="0" height="100" width="100" y="10" x="10"/><subproduct id="57330" name="" price="0" height="100" width="100" y="10" x="10"/><subproduct id="19582" name="" price="0" height="100" width="100" y="10" x="10"/><subproduct id="55701" name="" price="0" height="100" width="100" y="10" x="10"/><subproduct id="27452" name="" price="0" height="100" width="100" y="10" x="10"/><subproduct id="62064" name="" price="0" height="100" width="100" y="10" x="10"/><subproduct id="17056" name="" price="0" height="100" width="100" y="10" x="10"/><subproduct id="76435" name="" price="0" height="100" width="100" y="10" x="10"/><subproduct id="79424" name="" price="0" height="100" width="100" y="10" x="10"/><subproduct id="43218" name="" price="0" height="100" width="100" y="10" x="10"/><subproduct id="32017" name="" price="0" height="100" width="100" y="10" x="10"/><subproduct id="55106" name="" price="0" height="100" width="100" y="10" x="10"/><subproduct id="55107" name="" price="0" height="100" width="100" y="10" x="10"/><subproduct id="06110" name="" price="0" height="100" width="100" y="10" x="10"/><subproduct id="42819" name="" price="0" height="100" width="100" y="10" x="10"/><subproduct id="62061" name="" price="0" height="100" width="100" y="10" x="10"/><subproduct id="17870" name="" price="0" height="100" width="100" y="10" x="10"/><subproduct id="18806" name="" price="0" height="100" width="100" y="10" x="10"/><subproduct id="37966" name="" price="0" height="100" width="100" y="10" x="10"/><subproduct id="42385" name="სუნამოს წყალი Avon Luck (ეივონ ლაქ) - ნიმუში 0, мл" price="1" height="100" width="100" y="10" x="10"/><subproduct id="61303" name="" price="0" height="100" width="100" y="10" x="10"/><subproduct id="27534" name="" price="0" height="100" width="100" y="10" x="10"/><subproduct id="27779" name="" price="0" height="100" width="100" y="10" x="10"/><subproduct id="27537" name="სუნამოს წყალი Incandessence ( ინქანდესენს) - ნიმუში (0,6) მლ. 0, мл 1" price="0.5" height="100" width="100" y="10" x="10"/><subproduct id="59798" name="" price="0" height="100" width="100" y="10" x="10"/><subproduct id="58173" name="" price="0" height="100" width="100" y="10" x="10"/><subproduct id="23211" name="" price="0" height="100" width="100" y="10" x="10"/><subproduct id="27775" name="" price="0" height="100" width="100" y="10" x="10"/><subproduct id="78169" name="" price="0" height="100" width="100" y="10" x="10"/><subproduct id="48706" name="" price="0" height="100" width="100" y="10" x="10"/><subproduct id="26275" name="" price="0" height="100" width="100" y="10" x="10"/><subproduct id="15153" name="" price="0" height="100" width="100" y="10" x="10"/><subproduct id="36446" name="" price="0" height="100" width="100" y="10" x="10"/><subproduct id="19099" name="" price="0" height="100" width="100" y="10" x="10"/><subproduct id="32526" name="" price="0" height="100" width="100" y="10" x="10"/><subproduct id="91689" name="" price="0" height="100" width="100" y="10" x="10"/><subproduct id="62015" name="" price="0" height="100" width="100" y="10" x="10"/><subproduct id="58898" name="" price="0" height="100" width="100" y="10" x="10"/><subproduct id="61219" name="" price="0" height="100" width="100" y="10" x="10"/><subproduct id="36445" name="" price="0" height="100" width="100" y="10" x="10"/><subproduct id="36739" name="" price="0" height="100" width="100" y="10" x="10"/><subproduct id="25541" name="" price="0" height="100" width="100" y="10" x="10"/><subproduct id="07178" name="" price="0" height="100" width="100" y="10" x="10"/><subproduct id="31500" name="" price="0" height="100" width="100" y="10" x="10"/><subproduct id="06553" name="" price="0" height="100" width="100" y="10" x="10"/><subproduct id="38173" name="" price="0" height="100" width="100" y="10" x="10"/><subproduct id="45341" name="ტუალეტის წყალი Avon Luck (ეივონ ლაქ) -ნიმუში  0, мл" price="1" height="100" width="100" y="10" x="10"/><subproduct id="19780" name="" price="0" height="100" width="100" y="10" x="10"/><subproduct id="52009" name="" price="0" height="100" width="100" y="10" x="10"/><subproduct id="61498" name="" price="0" height="100" width="100" y="10" x="10"/><subproduct id="96640" name="" price="0" height="100" width="100" y="10" x="10"/><subproduct id="58533" name="" price="0" height="100" width="100" y="10" x="10"/><subproduct id="43346" name="" price="0" height="100" width="100" y="10" x="10"/><subproduct id="54686" name="" price="0" height="100" width="100" y="10" x="10"/></product></page><page addtobag="1" id="6" category=""><limage url="assets/images/large/012.jpg"/><mimage url="assets/images/medium/012.jpg"/><simage url="assets/images/small/012.jpg"/><product id="10839" name="" price="0" height="450" width="450" y="0" x="0"><subproduct id="43200" name="" price="0" height="100" width="100" y="10" x="10"/><subproduct id="77384" name="" price="0" height="100" width="100" y="10" x="10"/><subproduct id="79406" name="" price="0" height="100" width="100" y="10" x="10"/><subproduct id="91048" name="" price="0" height="100" width="100" y="10" x="10"/><subproduct id="78694" name="" price="0" height="100" width="100" y="10" x="10"/><subproduct id="79492" name="" price="0" height="100" width="100" y="10" x="10"/><subproduct id="77397" name="" price="0" height="100" width="100" y="10" x="10"/><subproduct id="37380" name="" price="0" height="100" width="100" y="10" x="10"/><subproduct id="79410" name="" price="0" height="100" width="100" y="10" x="10"/><subproduct id="37399" name="" price="0" height="100" width="100" y="10" x="10"/><subproduct id="37385" name="" price="0" height="100" width="100" y="10" x="10"/><subproduct id="79621" name="" price="0" height="100" width="100" y="10" x="10"/><subproduct id="91047" name="" price="0" height="100" width="100" y="10" x="10"/><subproduct id="37383" name="" price="0" height="100" width="100" y="10" x="10"/><subproduct id="37396" name="" price="0" height="100" width="100" y="10" x="10"/><subproduct id="37392" name="" price="0" height="100" width="100" y="10" x="10"/><subproduct id="79476" name="" price="0" height="100" width="100" y="10" x="10"/><subproduct id="77387" name="" price="0" height="100" width="100" y="10" x="10"/><subproduct id="33620" name="" price="0" height="100" width="100" y="10" x="10"/><subproduct id="75645" name="" price="0" height="100" width="100" y="10" x="10"/><subproduct id="14372" name="" price="0" height="100" width="100" y="10" x="10"/><subproduct id="12853" name="" price="0" height="100" width="100" y="10" x="10"/><subproduct id="13346" name="" price="0" height="100" width="100" y="10" x="10"/><subproduct id="12754" name="" price="0" height="100" width="100" y="10" x="10"/><subproduct id="12921" name="" price="0" height="100" width="100" y="10" x="10"/><subproduct id="12478" name="" price="0" height="100" width="100" y="10" x="10"/><subproduct id="13898" name="" price="0" height="100" width="100" y="10" x="10"/><subproduct id="13189" name="" price="0" height="100" width="100" y="10" x="10"/><subproduct id="09743" name="" price="0" height="100" width="100" y="10" x="10"/><subproduct id="13374" name="" price="0" height="100" width="100" y="10" x="10"/><subproduct id="13446" name="" price="0" height="100" width="100" y="10" x="10"/><subproduct id="12986" name="" price="0" height="100" width="100" y="10" x="10"/><subproduct id="13199" name="" price="0" height="100" width="100" y="10" x="10"/><subproduct id="14370" name="" price="0" height="100" width="100" y="10" x="10"/><subproduct id="12441" name="" price="0" height="100" width="100" y="10" x="10"/><subproduct id="14229" name="" price="0" height="100" width="100" y="10" x="10"/><subproduct id="13120" name="" price="0" height="100" width="100" y="10" x="10"/><subproduct id="12366" name="" price="0" height="100" width="100" y="10" x="10"/><subproduct id="14122" name="" price="0" height="100" width="100" y="10" x="10"/><subproduct id="12588" name="" price="0" height="100" width="100" y="10" x="10"/><subproduct id="86960" name="" price="0" height="100" width="100" y="10" x="10"/><subproduct id="11384" name="" price="0" height="100" width="100" y="10" x="10"/><subproduct id="10615" name="" price="0" height="100" width="100" y="10" x="10"/><subproduct id="10640" name="" price="0" height="100" width="100" y="10" x="10"/><subproduct id="10786" name="" price="0" height="100" width="100" y="10" x="10"/><subproduct id="11320" name="" price="0" height="100" width="100" y="10" x="10"/><subproduct id="11330" name="" price="0" height="100" width="100" y="10" x="10"/><subproduct id="11366" name="" price="0" height="100" width="100" y="10" x="10"/><subproduct id="10212" name="" price="0" height="100" width="100" y="10" x="10"/><subproduct id="11369" name="" price="0" height="100" width="100" y="10" x="10"/><subproduct id="11400" name="" price="0" height="100" width="100" y="10" x="10"/><subproduct id="10642" name="" price="0" height="100" width="100" y="10" x="10"/><subproduct id="10612" name="" price="0" height="100" width="100" y="10" x="10"/><subproduct id="11321" name="" price="0" height="100" width="100" y="10" x="10"/><subproduct id="10234" name="" price="0" height="100" width="100" y="10" x="10"/></product><product id="42685" name="" price="0" height="450" width="450" y="0" x="429"><subproduct id="28929" name="" price="0" height="100" width="100" y="10" x="10"/><subproduct id="98088" name="" price="0" height="100" width="100" y="10" x="10"/><subproduct id="15143" name="" price="0" height="100" width="100" y="10" x="10"/><subproduct id="12970" name="" price="0" height="100" width="100" y="10" x="10"/><subproduct id="17129" name="" price="0" height="100" width="100" y="10" x="10"/><subproduct id="15648" name="" price="0" height="100" width="100" y="10" x="10"/><subproduct id="16896" name="" price="0" height="100" width="100" y="10" x="10"/><subproduct id="38032" name="" price="0" height="100" width="100" y="10" x="10"/><subproduct id="35622" name="" price="0" height="100" width="100" y="10" x="10"/><subproduct id="37063" name="" price="0" height="100" width="100" y="10" x="10"/><subproduct id="35806" name="" price="0" height="100" width="100" y="10" x="10"/><subproduct id="09289" name="" price="0" height="100" width="100" y="10" x="10"/><subproduct id="93325" name="" price="0" height="100" width="100" y="10" x="10"/><subproduct id="35281" name="" price="0" height="100" width="100" y="10" x="10"/><subproduct id="35491" name="" price="0" height="100" width="100" y="10" x="10"/><subproduct id="35544" name="" price="0" height="100" width="100" y="10" x="10"/><subproduct id="34539" name="" price="0" height="100" width="100" y="10" x="10"/><subproduct id="33899" name="" price="0" height="100" width="100" y="10" x="10"/><subproduct id="34221" name="" price="0" height="100" width="100" y="10" x="10"/><subproduct id="40886" name="" price="0" height="100" width="100" y="10" x="10"/><subproduct id="57902" name="" price="0" height="100" width="100" y="10" x="10"/><subproduct id="72551" name="" price="0" height="100" width="100" y="10" x="10"/><subproduct id="31273" name="" price="0" height="100" width="100" y="10" x="10"/><subproduct id="30998" name="" price="0" height="100" width="100" y="10" x="10"/><subproduct id="72173" name="" price="0" height="100" width="100" y="10" x="10"/><subproduct id="72306" name="" price="0" height="100" width="100" y="10" x="10"/><subproduct id="42440" name="" price="0" height="100" width="100" y="10" x="10"/></product></page><page addtobag="1" id="7" category=""><limage url="assets/images/large/014.jpg"/><mimage url="assets/images/medium/014.jpg"/><simage url="assets/images/small/014.jpg"/></page><back addtobag="1" category=""><limage url="assets/images/large/back.jpg"/><mimage url="assets/images/medium/back.jpg"/><simage url="assets/images/small/back.jpg"/></back>
  <categories>
 <category value="" width="230"/> 
 	 </categories>

<omniture account="avonge" curr="GEL" qaeaccount="avonceeqa">
  <index value="CFT"/> 
  </omniture>
  </avon>
