<?xml version="1.0" encoding="UTF-8"?>
<avon total="3"><cover addtobag="1" category=""><limage url="assets/images/large/cover.jpg"/><mimage url="assets/images/medium/cover.jpg"/><simage url="assets/images/small/cover.jpg"/></cover><page addtobag="1" id="1" category=""><limage url="assets/images/large/002.jpg"/><mimage url="assets/images/medium/002.jpg"/><simage url="assets/images/small/002.jpg"/><product id="66740" name="Вішак Д/Шарфів" price="0" height="450" width="450" y="0" x="0"><subproduct id="96004" name="Жіноча Сумка &quot;Магдалина&quot;" price="0" height="100" width="100" y="10" x="10"/><subproduct id="60585" name="Жіноча Сумка &quot;Белла&quot; Чорна" price="0" height="100" width="100" y="10" x="10"/><subproduct id="47035" name="Лак Д/Нігтів &quot;Експерт Кольору&quot; Загадкова" price="0" height="100" width="100" y="10" x="10"/><subproduct id="13516" name="Лак Д/Нігтів &quot;Дизайнер Кольору&quot; Коралови" price="0" height="100" width="100" y="10" x="10"/><subproduct id="47034" name="Лак Д/Нігтів &quot;Експерт Кольору&quot; Весняний" price="0" height="100" width="100" y="10" x="10"/><subproduct id="12843" name="Лак Д/Нігтів &quot;Дизайнер Кольору&quot; Блакитна" price="0" height="100" width="100" y="10" x="10"/><subproduct id="13354" name="Лак Д/Нігтів &quot;Дизайнер Кольору&quot; Рожевий" price="0" height="100" width="100" y="10" x="10"/><subproduct id="13857" name="Лак Д/Нігтів &quot;Дизайнер Кольору&quot; Білий Сн" price="0" height="100" width="100" y="10" x="10"/><subproduct id="46700" name="Лак Д/Нігтів &quot;Експерт Кольору&quot; Лілова Тр" price="0" height="100" width="100" y="10" x="10"/><subproduct id="13884" name="Пензлик Д/Дизайну Нігтів" price="0" height="100" width="100" y="10" x="10"/><subproduct id="96018" name="Жіноча Сумка &quot;Рішель&quot;, Фіолетова" price="0" height="100" width="100" y="10" x="10"/><subproduct id="96020" name="Жіноча Сумка &quot;Рішель&quot;, Чорна" price="0" height="100" width="100" y="10" x="10"/><subproduct id="13517" name="Лак Д/Нігтів &quot;Дизайнер Кольору&quot; Золотист" price="0" height="100" width="100" y="10" x="10"/><subproduct id="40151" name="Жіноча Сумка &quot;Іла&quot;" price="0" height="100" width="100" y="10" x="10"/><subproduct id="09759" name="Тіні-Олів.Д/Повік&quot;Північне Сяйво&quot; М'Ятни" price="0" height="100" width="100" y="10" x="10"/><subproduct id="09109" name="Тіні-Олів.Д/Повік&quot;Північне Сяйво&quot; Ваніль" price="0" height="100" width="100" y="10" x="10"/><subproduct id="60119" name="Жіночий Шарф &quot;Белла&quot;" price="0" height="100" width="100" y="10" x="10"/><subproduct id="41656" name="Рукавички Жіночі" price="0" height="100" width="100" y="10" x="10"/><subproduct id="63935" name="Рукавички Чоловічі" price="0" height="100" width="100" y="10" x="10"/><subproduct id="90571" name="Жіночий Шарф &quot;Кріста&quot; (Круговий)" price="0" height="100" width="100" y="10" x="10"/><subproduct id="75208" name="Жіночий Шарф &quot;Ніколь&quot;" price="0" height="100" width="100" y="10" x="10"/><subproduct id="10397" name="Плед Розмір 165х130 См" price="0" height="100" width="100" y="10" x="10"/><subproduct id="52561" name="Аксесуар Д/Укладання Волосся. Бежевий" price="0" height="100" width="100" y="10" x="10"/><subproduct id="21188" name="Аксесуар Д/Укладання Волосся. Коричневий" price="0" height="100" width="100" y="10" x="10"/><subproduct id="27144" name="Плед, Розміри:170*125 См" price="0" height="100" width="100" y="10" x="10"/><subproduct id="86239" name="Жіночий Шарф &quot;Грейс&quot;" price="0" height="100" width="100" y="10" x="10"/></product><product id="27167" name="Косметичка, Розмір 20*14*5.5 См" price="0" height="450" width="450" y="0" x="429"><subproduct id="27412" name="Жіночий Гаманець. (З Синім Принтом)" price="0" height="100" width="100" y="10" x="10"/><subproduct id="27413" name="Жіночий Гаманець. (З Сріблястим Принтом)" price="0" height="100" width="100" y="10" x="10"/><subproduct id="27357" name="Жіночий Гаманець. (З Рожевим Принтом)" price="0" height="100" width="100" y="10" x="10"/><subproduct id="27319" name="Жіночий Гаманець(Зі Смарагдовим Принтом)" price="0" height="100" width="100" y="10" x="10"/><subproduct id="61108" name="Блокнот (80 Аркушів)" price="0" height="100" width="100" y="10" x="10"/><subproduct id="67947" name="Блокнот &quot;Кавун&quot;" price="0" height="100" width="100" y="10" x="10"/><subproduct id="68398" name="Блокнот &quot;Ківі&quot;" price="0" height="100" width="100" y="10" x="10"/><subproduct id="68205" name="Блокнот &quot;Апельсин&quot;" price="0" height="100" width="100" y="10" x="10"/><subproduct id="66055" name="Пляжний Рушник" price="0" height="100" width="100" y="10" x="10"/><subproduct id="53566" name="Рамка Д/Фотографій" price="0" height="100" width="100" y="10" x="10"/><subproduct id="27992" name="Набір Декоративних Серветок (4 Шт.)" price="0" height="100" width="100" y="10" x="10"/><subproduct id="71187" name="Органайзер Для Аксесуарів" price="0" height="100" width="100" y="10" x="10"/><subproduct id="35772" name="Апарат Д/Косметичних Процедур" price="0" height="100" width="100" y="10" x="10"/><subproduct id="92474" name="Кружка" price="0" height="100" width="100" y="10" x="10"/><subproduct id="02046" name="Зовнішній Акумулятор" price="0" height="100" width="100" y="10" x="10"/><subproduct id="01251" name="Багатофункціональний Брелок &quot;7-В-1&quot;" price="0" height="100" width="100" y="10" x="10"/><subproduct id="02102" name="Багатофункціональна Ручка 5-В-1" price="0" height="100" width="100" y="10" x="10"/><subproduct id="77273" name="Набір Інтер.Прикрас Зі Світлов.Ефект.2шт" price="0" height="100" width="100" y="10" x="10"/><subproduct id="91259" name="Настільний Кварцовий Годинник-Динамік" price="0" height="100" width="100" y="10" x="10"/></product></page><page addtobag="1" id="2" category=""><limage url="assets/images/large/004.jpg"/><mimage url="assets/images/medium/004.jpg"/><simage url="assets/images/small/004.jpg"/><product id="88890" name="Штани Для Дівчат, 7-8 Років" price="0" height="450" width="450" y="0" x="0"><subproduct id="85087" name="Дитяча Піжама Д/Дівчаток. 3-4 Років" price="0" height="100" width="100" y="10" x="10"/><subproduct id="85089" name="Дитяча Піжама Д/Дівчаток. 5-6 Років" price="0" height="100" width="100" y="10" x="10"/><subproduct id="85217" name="Дитяча Піжама Д/Дівчаток. 7-8 Років" price="0" height="100" width="100" y="10" x="10"/><subproduct id="02381" name="Жіноча Піжама &quot;Париж&quot;. Розмір: 40/42" price="0" height="100" width="100" y="10" x="10"/><subproduct id="02688" name="Жіноча Піжама &quot;Париж&quot;. Розмір: 52/54" price="0" height="100" width="100" y="10" x="10"/><subproduct id="68097" name="Жіноча Піжама. Розмір: 40/42" price="0" height="100" width="100" y="10" x="10"/><subproduct id="68161" name="Жіноча Піжама. Розмір: 44/46" price="0" height="100" width="100" y="10" x="10"/><subproduct id="69028" name="Жіноча Піжама. Розмір: 56/58" price="0" height="100" width="100" y="10" x="10"/><subproduct id="90744" name="Жіноча Футболка (Синя) Розмір: 40/42" price="0" height="100" width="100" y="10" x="10"/><subproduct id="91168" name="Жіноча Футболка (Синя) Розмір: 44/46" price="0" height="100" width="100" y="10" x="10"/><subproduct id="92769" name="Жіноча Футболка (Червона) Розмір: 40/42" price="0" height="100" width="100" y="10" x="10"/><subproduct id="92770" name="Жіноча Футболка (Червона) Розмір: 44/46" price="0" height="100" width="100" y="10" x="10"/><subproduct id="92782" name="Жіноча Футболка (Червона) Розмір: 48/50" price="0" height="100" width="100" y="10" x="10"/><subproduct id="92795" name="Жіноча Футболка (Червона) Розмір: 56/58" price="0" height="100" width="100" y="10" x="10"/><subproduct id="62118" name="Дитяча Сукня (Для Дітей 3-4 Років)" price="0" height="100" width="100" y="10" x="10"/><subproduct id="62320" name="Дитяча Сукня (Для Дітей 5-6 Років)" price="0" height="100" width="100" y="10" x="10"/><subproduct id="62372" name="Дитяча Сукня (Для Дітей 7-8 Років)" price="0" height="100" width="100" y="10" x="10"/><subproduct id="78631" name="Дитяча Піжама Д/Дівчаток. 3-4 Років" price="0" height="100" width="100" y="10" x="10"/><subproduct id="01875" name="Одяг Жіночий.Сукня.Розмір 40-42" price="0" height="100" width="100" y="10" x="10"/><subproduct id="02048" name="Одяг Жіночий.Сукня.Розмір 44-46" price="0" height="100" width="100" y="10" x="10"/><subproduct id="02481" name="Одяг Жіночий.Сукня.Розмір 56-58" price="0" height="100" width="100" y="10" x="10"/><subproduct id="91780" name="Жін.Дом.Одяг:Футболка,Штани Розмір 40-42" price="0" height="100" width="100" y="10" x="10"/><subproduct id="91789" name="Жін.Дом.Одяг:Футболка,Штани Розмір 44-46" price="0" height="100" width="100" y="10" x="10"/><subproduct id="91830" name="Жін.Дом.Одяг:Футболка,Штани Розмір 48-50" price="0" height="100" width="100" y="10" x="10"/><subproduct id="91886" name="Жін.Дом.Одяг:Футболка,Штани Розмір 52-54" price="0" height="100" width="100" y="10" x="10"/><subproduct id="90352" name="Жін.Дом.Одяг:Футболка,Штани Розмір 56-58" price="0" height="100" width="100" y="10" x="10"/><subproduct id="77029" name="Дитячий Джемпер Д/Дівчаток, 3-4 Роки" price="0" height="100" width="100" y="10" x="10"/><subproduct id="78307" name="Дитячий Джемпер Д/Дівчаток, 7-8 Років" price="0" height="100" width="100" y="10" x="10"/><subproduct id="65566" name="Жіноча Блуза Р.42-44 Квіти" price="0" height="100" width="100" y="10" x="10"/><subproduct id="66104" name="Жіноча Блуза Р.54-56 Квіти" price="0" height="100" width="100" y="10" x="10"/><subproduct id="66886" name="Жіноча Блуза Р.58-60 Квіти" price="0" height="100" width="100" y="10" x="10"/><subproduct id="20368" name="Жіночі Легінси Р.42-44 В Клітинку" price="0" height="100" width="100" y="10" x="10"/><subproduct id="20443" name="Жіночі Легінси Р.46-48 В Клітинку" price="0" height="100" width="100" y="10" x="10"/><subproduct id="20716" name="Жіночі Легінси Р.50-52 В Клітинку" price="0" height="100" width="100" y="10" x="10"/><subproduct id="69024" name="Жіночі Штани. Розмір 40-42" price="0" height="100" width="100" y="10" x="10"/><subproduct id="69040" name="Жіночі Штани. Розмір 44-46" price="0" height="100" width="100" y="10" x="10"/><subproduct id="69227" name="Жіночі Штани. Розмір 52-54" price="0" height="100" width="100" y="10" x="10"/><subproduct id="49038" name="Жіноча Куртка. Розмір 40-42" price="0" height="100" width="100" y="10" x="10"/><subproduct id="49126" name="Жіноча Куртка. Розмір 44-46" price="0" height="100" width="100" y="10" x="10"/><subproduct id="49496" name="Жіноча Куртка. Розмір 48-50" price="0" height="100" width="100" y="10" x="10"/><subproduct id="49630" name="Жіноча Куртка. Розмір 52-54" price="0" height="100" width="100" y="10" x="10"/><subproduct id="27516" name="Жін.Спідниця&quot;Витончений Силует&quot;Р.58-60" price="0" height="100" width="100" y="10" x="10"/><subproduct id="86904" name="Жіноче Пончо &quot;Ава&quot;, Розмір 48-54" price="0" height="100" width="100" y="10" x="10"/><subproduct id="86763" name="Жіноче Пончо &quot;Ава&quot;, Розмір 40-46" price="0" height="100" width="100" y="10" x="10"/><subproduct id="88957" name="Штани Для Дівчат, 3-4 Роки" price="0" height="100" width="100" y="10" x="10"/><subproduct id="88958" name="Штани Для Дівчат, 5-6 Років" price="0" height="100" width="100" y="10" x="10"/></product><product id="09689" name="Жіночі Чоботи, Розмір 40" price="0" height="450" width="450" y="0" x="429"><subproduct id="03794" name="Труси Чоловічі, Розмір S" price="0" height="100" width="100" y="10" x="10"/><subproduct id="04187" name="Труси Чоловічі, Розмір M" price="0" height="100" width="100" y="10" x="10"/><subproduct id="04333" name="Труси Чоловічі, Розмір L" price="0" height="100" width="100" y="10" x="10"/><subproduct id="04365" name="Труси Чоловічі, Розмір Xl" price="0" height="100" width="100" y="10" x="10"/><subproduct id="78063" name="Жіночий Купальний Костюм. Верх 40/42" price="0" height="100" width="100" y="10" x="10"/><subproduct id="78560" name="Жіночий Купальний Костюм. Верх: 52/54" price="0" height="100" width="100" y="10" x="10"/><subproduct id="60114" name="Корсет (Розмір 42-44)" price="0" height="100" width="100" y="10" x="10"/><subproduct id="59180" name="Корсет Розмір 42-44" price="0" height="100" width="100" y="10" x="10"/><subproduct id="59184" name="Корсет Розмір 54-56" price="0" height="100" width="100" y="10" x="10"/><subproduct id="19337" name="Боді, Розмір 40-42" price="0" height="100" width="100" y="10" x="10"/><subproduct id="19339" name="Боді, Розмір 44-46" price="0" height="100" width="100" y="10" x="10"/><subproduct id="19340" name="Боді, Розмір 48-50" price="0" height="100" width="100" y="10" x="10"/><subproduct id="19976" name="Боді, Розмір 52-54" price="0" height="100" width="100" y="10" x="10"/><subproduct id="19978" name="Боді, Розмір 56-58" price="0" height="100" width="100" y="10" x="10"/><subproduct id="45165" name="Балетки (Рожеві). Розмір: 36" price="0" height="100" width="100" y="10" x="10"/><subproduct id="34972" name="Балетки (Рожеві). Розмір: 37" price="0" height="100" width="100" y="10" x="10"/><subproduct id="35121" name="Балетки (Рожеві). Розмір: 38" price="0" height="100" width="100" y="10" x="10"/><subproduct id="35751" name="Балетки (Рожеві). Розмір: 39" price="0" height="100" width="100" y="10" x="10"/><subproduct id="35763" name="Балетки (Рожеві). Розмір: 40" price="0" height="100" width="100" y="10" x="10"/><subproduct id="35764" name="Балетки (Рожеві). Розмір: 41" price="0" height="100" width="100" y="10" x="10"/><subproduct id="43282" name="Балетки (Сірі). Розмір: 36" price="0" height="100" width="100" y="10" x="10"/><subproduct id="43355" name="Балетки (Сірі). Розмір: 37" price="0" height="100" width="100" y="10" x="10"/><subproduct id="43435" name="Балетки (Сірі). Розмір: 38" price="0" height="100" width="100" y="10" x="10"/><subproduct id="43444" name="Балетки (Сірі). Розмір: 39" price="0" height="100" width="100" y="10" x="10"/><subproduct id="43548" name="Балетки (Сірі). Розмір: 40" price="0" height="100" width="100" y="10" x="10"/><subproduct id="43552" name="Балетки (Сірі). Розмір: 41" price="0" height="100" width="100" y="10" x="10"/><subproduct id="43132" name="Балетки (Коричневі). Розмір: 36" price="0" height="100" width="100" y="10" x="10"/><subproduct id="43135" name="Балетки (Коричневі). Розмір: 37" price="0" height="100" width="100" y="10" x="10"/><subproduct id="43163" name="Балетки (Коричневі). Розмір: 38" price="0" height="100" width="100" y="10" x="10"/><subproduct id="43165" name="Балетки (Коричневі). Розмір: 39" price="0" height="100" width="100" y="10" x="10"/><subproduct id="43229" name="Балетки (Коричневі). Розмір: 40" price="0" height="100" width="100" y="10" x="10"/><subproduct id="43280" name="Балетки (Коричневі). Розмір: 41" price="0" height="100" width="100" y="10" x="10"/><subproduct id="15809" name="Труси Жіночі. Чорні. Розмір: 44/46" price="0" height="100" width="100" y="10" x="10"/><subproduct id="15811" name="Труси Жіночі. Чорні. Розмір: 48/50" price="0" height="100" width="100" y="10" x="10"/><subproduct id="15815" name="Труси Жіночі. Чорні. Розмір: 56/58" price="0" height="100" width="100" y="10" x="10"/><subproduct id="90097" name="Жіноча Майка Розмір 42-44" price="0" height="100" width="100" y="10" x="10"/><subproduct id="90188" name="Жіноча Майка Розмір 54-56" price="0" height="100" width="100" y="10" x="10"/><subproduct id="90213" name="Жіноча Майка Розмір 58-60" price="0" height="100" width="100" y="10" x="10"/><subproduct id="90722" name="Жіночий Купальний Костюм. Низ. 40/42" price="0" height="100" width="100" y="10" x="10"/><subproduct id="90735" name="Жіночий Купальний Костюм. Низ: 52/54" price="0" height="100" width="100" y="10" x="10"/><subproduct id="72181" name="Жіночі Еспадрильї. Розмір 36" price="0" height="100" width="100" y="10" x="10"/><subproduct id="72286" name="Жіночі Еспадрильї. Розмір 37" price="0" height="100" width="100" y="10" x="10"/><subproduct id="72608" name="Жіночі Еспадрильї. Розмір 38" price="0" height="100" width="100" y="10" x="10"/><subproduct id="72611" name="Жіночі Еспадрильї. Розмір 39" price="0" height="100" width="100" y="10" x="10"/><subproduct id="72629" name="Жіночі Еспадрильї. Розмір 40" price="0" height="100" width="100" y="10" x="10"/><subproduct id="72799" name="Жіночі Еспадрильї. Розмір 41" price="0" height="100" width="100" y="10" x="10"/><subproduct id="71706" name="Жіночі Еспадрильї(Сірі). Розмір 36" price="0" height="100" width="100" y="10" x="10"/><subproduct id="72095" name="Жіночі Еспадрильї(Сірі). Розмір 37" price="0" height="100" width="100" y="10" x="10"/><subproduct id="72096" name="Жіночі Еспадрильї(Сірі). Розмір 38" price="0" height="100" width="100" y="10" x="10"/><subproduct id="72104" name="Жіночі Еспадрильї(Сірі). Розмір 39" price="0" height="100" width="100" y="10" x="10"/><subproduct id="72110" name="Жіночі Еспадрильї(Сірі). Розмір 40" price="0" height="100" width="100" y="10" x="10"/><subproduct id="72111" name="Жіночі Еспадрильї(Сірі). Розмір 41" price="0" height="100" width="100" y="10" x="10"/><subproduct id="56916" name="Жіноча Сукня, Розмір 40-42" price="0" height="100" width="100" y="10" x="10"/><subproduct id="56923" name="Жіноча Сукня, Розмір 44-46" price="0" height="100" width="100" y="10" x="10"/><subproduct id="56959" name="Жіноча Сукня, Розмір 48-50" price="0" height="100" width="100" y="10" x="10"/><subproduct id="57655" name="Жіноча Сукня, Розмір 52-54" price="0" height="100" width="100" y="10" x="10"/><subproduct id="57764" name="Жіноча Сукня, Розмір 56-58" price="0" height="100" width="100" y="10" x="10"/><subproduct id="25960" name="Жіноч.Сукня &quot;Витончений Силует&quot; Р. 40/42" price="0" height="100" width="100" y="10" x="10"/><subproduct id="28345" name="Жіноч.Сукня &quot;Витончений Силует&quot; Р. 56/58" price="0" height="100" width="100" y="10" x="10"/><subproduct id="47530" name="Балетки, Розмір 36" price="0" height="100" width="100" y="10" x="10"/><subproduct id="47580" name="Балетки, Розмір 37" price="0" height="100" width="100" y="10" x="10"/><subproduct id="49455" name="Балетки, Розмір 38" price="0" height="100" width="100" y="10" x="10"/><subproduct id="49476" name="Балетки, Розмір 39" price="0" height="100" width="100" y="10" x="10"/><subproduct id="50585" name="Балетки, Розмір 40" price="0" height="100" width="100" y="10" x="10"/><subproduct id="50612" name="Балетки, Розмір 41" price="0" height="100" width="100" y="10" x="10"/><subproduct id="99632" name="Жіночі Кросівки. Чорні. Розмір: 37" price="0" height="100" width="100" y="10" x="10"/><subproduct id="99503" name="Жіночі Кросівки. Рожеві. Розмір: 37" price="0" height="100" width="100" y="10" x="10"/><subproduct id="99506" name="Жіночі Кросівки. Рожеві. Розмір: 39" price="0" height="100" width="100" y="10" x="10"/><subproduct id="11140" name="Жіночі Кросівки, Розмір 36" price="0" height="100" width="100" y="10" x="10"/><subproduct id="11141" name="Жіночі Кросівки, Розмір 37" price="0" height="100" width="100" y="10" x="10"/><subproduct id="04849" name="Жіночі Чоботи, Розмір 36" price="0" height="100" width="100" y="10" x="10"/><subproduct id="05252" name="Жіночі Чоботи, Розмір 37" price="0" height="100" width="100" y="10" x="10"/><subproduct id="07598" name="Жіночі Чоботи, Розмір 38" price="0" height="100" width="100" y="10" x="10"/></product></page><page addtobag="1" id="3" category=""><limage url="assets/images/large/006.jpg"/><mimage url="assets/images/medium/006.jpg"/><simage url="assets/images/small/006.jpg"/><product id="89320" name="Набір Сережок &quot;Меган&quot;" price="0" height="450" width="450" y="0" x="0"><subproduct id="64084" name="Набір Шармів &quot;Джері&quot; (3 Шт)" price="0" height="100" width="100" y="10" x="10"/><subproduct id="54181" name="Кольє &quot;Азура&quot;" price="0" height="100" width="100" y="10" x="10"/><subproduct id="60047" name="Браслет &quot;Робін&quot; Січень" price="0" height="100" width="100" y="10" x="10"/><subproduct id="60065" name="Браслет &quot;Робін&quot; Лютий" price="0" height="100" width="100" y="10" x="10"/><subproduct id="60069" name="Браслет &quot;Робін&quot; Березень" price="0" height="100" width="100" y="10" x="10"/><subproduct id="60073" name="Браслет &quot;Робін&quot; Квітень" price="0" height="100" width="100" y="10" x="10"/><subproduct id="60124" name="Браслет &quot;Робін&quot; Травень" price="0" height="100" width="100" y="10" x="10"/><subproduct id="60288" name="Браслет &quot;Робін&quot; Липень" price="0" height="100" width="100" y="10" x="10"/><subproduct id="60302" name="Браслет &quot;Робін&quot; Серпень" price="0" height="100" width="100" y="10" x="10"/><subproduct id="60303" name="Браслет &quot;Робін&quot; Вересень" price="0" height="100" width="100" y="10" x="10"/><subproduct id="60304" name="Браслет &quot;Робін&quot; Жовтень" price="0" height="100" width="100" y="10" x="10"/><subproduct id="61179" name="Браслет &quot;Робін&quot; Листопад" price="0" height="100" width="100" y="10" x="10"/><subproduct id="60278" name="Браслет &quot;Робін&quot; Червень" price="0" height="100" width="100" y="10" x="10"/><subproduct id="63404" name="Браслет &quot;Робін&quot; Грудень" price="0" height="100" width="100" y="10" x="10"/><subproduct id="68889" name="Кольє &quot;Енджі&quot;" price="0" height="100" width="100" y="10" x="10"/><subproduct id="64139" name="Браслет &quot;Міла&quot;" price="0" height="100" width="100" y="10" x="10"/><subproduct id="07292" name="Кольє &quot;Нішель&quot;" price="0" height="100" width="100" y="10" x="10"/><subproduct id="76012" name="Набір Шармів &quot;Джианна&quot; (3шт)" price="0" height="100" width="100" y="10" x="10"/><subproduct id="76047" name="Набір Сережок &quot;Ембер&quot; (7 Пар)" price="0" height="100" width="100" y="10" x="10"/><subproduct id="51495" name="Кольє &quot;Керрі&quot;" price="0" height="100" width="100" y="10" x="10"/><subproduct id="66765" name="Набір Прикрас &quot;Сесилія&quot;" price="0" height="100" width="100" y="10" x="10"/><subproduct id="98498" name="Комплект Біжутерії &quot;Бріелла&quot;" price="0" height="100" width="100" y="10" x="10"/><subproduct id="68279" name="Кольє &quot;Бренда&quot;" price="0" height="100" width="100" y="10" x="10"/><subproduct id="06090" name="Набір Прикрас &quot;Осанна&quot;:Браслет+Кольє-Чок" price="0" height="100" width="100" y="10" x="10"/><subproduct id="78944" name="Набір Прикрас &quot;Джолін&quot;" price="0" height="100" width="100" y="10" x="10"/></product><product id="73530" name="Набір Для Манікюру" price="0" height="450" width="450" y="0" x="429"><subproduct id="90811" name="Браслет &quot;Лев&quot;" price="0" height="100" width="100" y="10" x="10"/><subproduct id="91019" name="Браслет &quot;Рак&quot;" price="0" height="100" width="100" y="10" x="10"/><subproduct id="91633" name="Браслет &quot;Водолій&quot;" price="0" height="100" width="100" y="10" x="10"/><subproduct id="91055" name="Браслет &quot;Скорпіон&quot;" price="0" height="100" width="100" y="10" x="10"/><subproduct id="90836" name="Браслет &quot;Близнюки&quot;" price="0" height="100" width="100" y="10" x="10"/><subproduct id="91008" name="Браслет &quot;Стрілець&quot;" price="0" height="100" width="100" y="10" x="10"/><subproduct id="90912" name="Браслет &quot;Діва&quot;" price="0" height="100" width="100" y="10" x="10"/><subproduct id="94709" name="Браслет &quot;Козеріг&quot;" price="0" height="100" width="100" y="10" x="10"/><subproduct id="90963" name="Браслет &quot;Риби&quot;" price="0" height="100" width="100" y="10" x="10"/><subproduct id="90973" name="Браслет &quot;Телець&quot;" price="0" height="100" width="100" y="10" x="10"/><subproduct id="91026" name="Браслет &quot;Терези&quot;" price="0" height="100" width="100" y="10" x="10"/><subproduct id="90810" name="Браслет &quot;Овен&quot;" price="0" height="100" width="100" y="10" x="10"/><subproduct id="92602" name="Кольє &quot;Рак&quot;" price="0" height="100" width="100" y="10" x="10"/><subproduct id="92712" name="Кольє &quot;Телець&quot;" price="0" height="100" width="100" y="10" x="10"/><subproduct id="92574" name="Кольє &quot;Лев&quot;" price="0" height="100" width="100" y="10" x="10"/><subproduct id="92630" name="Кольє &quot;Діва&quot;" price="0" height="100" width="100" y="10" x="10"/><subproduct id="92597" name="Кольє &quot;Стрілець&quot;" price="0" height="100" width="100" y="10" x="10"/><subproduct id="92618" name="Кольє &quot;Близнюки&quot;" price="0" height="100" width="100" y="10" x="10"/><subproduct id="93213" name="Кольє &quot;Овен&quot;" price="0" height="100" width="100" y="10" x="10"/><subproduct id="92575" name="Кольє &quot;Скорпіон&quot;" price="0" height="100" width="100" y="10" x="10"/><subproduct id="92562" name="Кольє &quot;Водолій&quot;" price="0" height="100" width="100" y="10" x="10"/><subproduct id="93203" name="Кольє &quot;Риби&quot;" price="0" height="100" width="100" y="10" x="10"/><subproduct id="92560" name="Кольє &quot;Терези&quot;" price="0" height="100" width="100" y="10" x="10"/><subproduct id="95123" name="Кольє &quot;Козеріг&quot;" price="0" height="100" width="100" y="10" x="10"/><subproduct id="88995" name="Набір Сережок &quot;Тоні&quot; (6 Пар)" price="0" height="100" width="100" y="10" x="10"/><subproduct id="65631" name="Набір Прикрас &quot;Гранат&quot;" price="0" height="100" width="100" y="10" x="10"/><subproduct id="65803" name="Набір Прикрас &quot;Смарагд&quot;" price="0" height="100" width="100" y="10" x="10"/><subproduct id="66651" name="Набір Прикрас &quot;Сапфір&quot;" price="0" height="100" width="100" y="10" x="10"/><subproduct id="65634" name="Набір Прикрас &quot;Аметист&quot;" price="0" height="100" width="100" y="10" x="10"/><subproduct id="65809" name="Набір Прикрас &quot;Світлий-Аметист&quot;" price="0" height="100" width="100" y="10" x="10"/><subproduct id="68141" name="Набір Прикрас &quot;Рожевий&quot;" price="0" height="100" width="100" y="10" x="10"/><subproduct id="54350" name="Набір Сережок &quot;Лора&quot;Сережки(3 Пари)Оправ" price="0" height="100" width="100" y="10" x="10"/><subproduct id="65635" name="Набір Прикрас &quot;Аквамарин&quot;" price="0" height="100" width="100" y="10" x="10"/><subproduct id="66633" name="Набір Прикрас &quot;Світло-Червоний&quot;" price="0" height="100" width="100" y="10" x="10"/><subproduct id="68145" name="Набір Прикрас &quot;Топаз&quot;" price="0" height="100" width="100" y="10" x="10"/><subproduct id="65735" name="Набір Прикрас &quot;Кристал&quot;" price="0" height="100" width="100" y="10" x="10"/><subproduct id="66643" name="Набір Прикрас &quot;Світло-Зелений&quot;" price="0" height="100" width="100" y="10" x="10"/><subproduct id="39982" name="Каблучка &quot;Еверлі&quot; Розмір: 6" price="0" height="100" width="100" y="10" x="10"/><subproduct id="41222" name="Каблучка &quot;Еверлі&quot; Розмір: 8" price="0" height="100" width="100" y="10" x="10"/><subproduct id="90689" name="Резинка Дял Волосся &quot;Веллі&quot;" price="0" height="100" width="100" y="10" x="10"/><subproduct id="27339" name="Жіночий Наручний Годинник &quot;Матільда&quot;" price="0" height="100" width="100" y="10" x="10"/><subproduct id="90574" name="Набір Заколок Для Волосся &quot;Керрі&quot;(5 Шт)" price="0" height="100" width="100" y="10" x="10"/><subproduct id="55425" name="Каблучка &quot;Крістін&quot;, Розмір 6" price="0" height="100" width="100" y="10" x="10"/><subproduct id="87763" name="Каблучка &quot;Крістін&quot;, Розмір 8" price="0" height="100" width="100" y="10" x="10"/><subproduct id="08120" name="Брошка &quot;Джейсі&quot;" price="0" height="100" width="100" y="10" x="10"/><subproduct id="96171" name="Сережки &quot;Яні&quot;" price="0" height="100" width="100" y="10" x="10"/></product></page><back addtobag="1" category=""><limage url="assets/images/large/back.jpg"/><mimage url="assets/images/medium/back.jpg"/><simage url="assets/images/small/back.jpg"/><product id="93289" name="Сонцезах.Крем Д/Дитячої Шкіри Spf 50" price="0" height="450" width="450" y="0" x="0"><subproduct id="79891" name="Набір Кремів Для Рук &quot;Доглянуті Ручки&quot;" price="0" height="100" width="100" y="10" x="10"/><subproduct id="50954" name="Набір Д/Педикюру" price="0" height="100" width="100" y="10" x="10"/><subproduct id="85369" name="Гель Д/Душу З Ароматом Журавлини І Кориц" price="0" height="100" width="100" y="10" x="10"/><subproduct id="97838" name="Віднов. Зволож. Крем-Суфле Для Тіла" price="0" height="100" width="100" y="10" x="10"/><subproduct id="20610" name="Рушник, Розмір 150*55 См" price="0" height="100" width="100" y="10" x="10"/><subproduct id="66675" name="Рушник" price="0" height="100" width="100" y="10" x="10"/><subproduct id="85037" name="Лосьйон Д/Тіла З Ароматом Журавлини І Ко" price="0" height="100" width="100" y="10" x="10"/><subproduct id="76700" name="Лосьйон Д/Тіла&quot;Інтенсивне Віднов&quot;Льон/Ма" price="0" height="100" width="100" y="10" x="10"/><subproduct id="18536" name="Лосьйон Д/Тіла&quot;Максимальне Зволоження&quot;Чі" price="0" height="100" width="100" y="10" x="10"/><subproduct id="41379" name="Крем Д/Тіла&quot;Оксамитова М'Якість/Звол&quot;Чіа" price="0" height="100" width="100" y="10" x="10"/><subproduct id="70144" name="Піна Д/Ванни З Ароматом Орхідеї 250мл" price="0" height="100" width="100" y="10" x="10"/><subproduct id="18137" name="Лосьйон Д/Тіла&quot;Глибоке Живлення&quot;З Мигдал" price="0" height="100" width="100" y="10" x="10"/><subproduct id="87495" name="Лосьйон Д/Тіла&quot;Зміцнення І Тонус&quot;З Бабас" price="0" height="100" width="100" y="10" x="10"/></product></back>

	<categories>
 		 <category value="" width="200"/> 
 	 </categories>

	<omniture account="avonua" qaeaccount="avonceeqa" curr="UAH">
		<index value="CFT"/>
	</omniture>

</avon>
